spfluo/__init__.py
spfluo/conftest.py
spfluo/ab_initio_reconstruction/README.md
spfluo/ab_initio_reconstruction/__init__.py
spfluo/ab_initio_reconstruction/__main__.py
spfluo/ab_initio_reconstruction/api.py
spfluo/ab_initio_reconstruction/params.py
spfluo/ab_initio_reconstruction/ruff.toml
spfluo/ab_initio_reconstruction/visualisation.py
spfluo/ab_initio_reconstruction/common_image_processing_methods/__init__.py
spfluo/ab_initio_reconstruction/common_image_processing_methods/others.py
spfluo/ab_initio_reconstruction/common_image_processing_methods/registration.py
spfluo/ab_initio_reconstruction/common_image_processing_methods/rotation_translation.py
spfluo/ab_initio_reconstruction/learning_algorithms/__init__.py
spfluo/ab_initio_reconstruction/learning_algorithms/gradient_descent_importance_sampling.py
spfluo/ab_initio_reconstruction/tests/__init__.py
spfluo/ab_initio_reconstruction/tests/main_test.py
spfluo/ab_initio_reconstruction/tests/test_ab_initio.py
spfluo/ab_initio_reconstruction/volume_representation/__init__.py
spfluo/ab_initio_reconstruction/volume_representation/pixel_representation.py
spfluo/ab_initio_reconstruction/volume_representation/gaussian_mixture_representation/GMM_grid_evaluation.py
spfluo/alignement/README.md
spfluo/alignement/__init__.py
spfluo/alignement/get_poses.py
spfluo/alignement/main.py
spfluo/data/.gitignore
spfluo/data/README.md
spfluo/data/__init__.py
spfluo/data/constants.py
spfluo/data/data.py
spfluo/data/generate_data.py
spfluo/data/make_registry.py
spfluo/data/registry.txt
spfluo/data/upload.py
spfluo/manual_picking/__main__.py
spfluo/manual_picking/annotate.py
spfluo/manual_picking/tests/test_annotate.py
spfluo/picking/README.md
spfluo/picking/__init__.py
spfluo/picking/__main__.py
spfluo/picking/modules/__init__.py
spfluo/picking/modules/config.py
spfluo/picking/modules/utils.py
spfluo/picking/modules/annotating/__init__.py
spfluo/picking/modules/annotating/extract.py
spfluo/picking/modules/posttraining/__init__.py
spfluo-0.1.0.dist-info/METADATA
spfluo-0.1.0.dist-info/WHEEL
spfluo-0.1.0.dist-info/RECORD
